pyhoox/__init__.py
pyhoox/core/__init__.py
pyhoox/core/async_registry.py
pyhoox/core/context.py
pyhoox/core/registry.py
pyhoox/features/__init__.py
pyhoox/features/decorators.py
pyhoox/features/middleware.py
pyhoox/features/monitoring.py
pyhoox/features/persistence.py
pyhoox/features/validation.py
pyhoox/initializer.py
pyhoox/main.py
pyhoox/types.py
pyhoox/utils/__init__.py
pyhoox-2.1.0.dist-info/LICENSE
pyhoox-2.1.0.dist-info/METADATA
pyhoox-2.1.0.dist-info/WHEEL
pyhoox-2.1.0.dist-info/entry_points.txt
pyhoox-2.1.0.dist-info/RECORD
