Metadata-Version: 2.1
Name: pyhoox
Version: 2.1.0
Summary: Advanced Python Hook System - Modular, type-safe, and feature-rich event management library
Home-page: https://github.com/techatlasdev/pyhoox
License: MIT
Keywords: hooks,events,callbacks,async,middleware,plugins
Author: techatlasdev
Author-email: srgoqui@gmail.com
Requires-Python: >=3.9,<4.0
Classifier: Development Status :: 5 - Production/Stable
Classifier: Intended Audience :: Developers
Classifier: License :: OSI Approved :: MIT License
Classifier: Operating System :: OS Independent
Classifier: Programming Language :: Python :: 3
Classifier: Programming Language :: Python :: 3.9
Classifier: Programming Language :: Python :: 3.10
Classifier: Programming Language :: Python :: 3.11
Classifier: Programming Language :: Python :: 3.12
Classifier: Programming Language :: Python :: 3.13
Classifier: Topic :: Software Development :: Libraries :: Python Modules
Classifier: Topic :: System :: Logging
Classifier: Typing :: Typed
Project-URL: Repository, https://github.com/techatlasdev/pyhoox
